MANIFEST.in
README.md
VERSION
requirements.txt
setup.cfg
setup.py
rhasspy_fuzzywuzzy.egg-info/PKG-INFO
rhasspy_fuzzywuzzy.egg-info/SOURCES.txt
rhasspy_fuzzywuzzy.egg-info/dependency_links.txt
rhasspy_fuzzywuzzy.egg-info/requires.txt
rhasspy_fuzzywuzzy.egg-info/top_level.txt
rhasspyfuzzywuzzy/__init__.py
rhasspyfuzzywuzzy/__main__.py
rhasspyfuzzywuzzy/const.py
rhasspyfuzzywuzzy/py.typed
rhasspyfuzzywuzzy/train.py
tests/__init__.py
tests/test_recognize.py